rizz/__init__.py
rizz/douhavetherizz.py
no_rizz-1.0.2.dist-info/METADATA
no_rizz-1.0.2.dist-info/WHEEL
no_rizz-1.0.2.dist-info/top_level.txt
no_rizz-1.0.2.dist-info/RECORD
