Metadata-Version: 2.1
Name: no-rizz
Version: 1.0.2
Summary: UNKNOWN
Home-page: UNKNOWN
License: UNKNOWN
Platform: UNKNOWN
Classifier: Programming Language :: Python :: 3
Classifier: License :: OSI Approved :: MIT License
Classifier: Operating System :: OS Independent
Requires-Python: >=3.6
Requires-Dist: google-auth-oauthlib >=1.2.1
Requires-Dist: google-api-python-client >=2.154.0
